LICENSE
README.md
setup.py
tap_oracle/__init__.py
tap_oracle/db.py
tap_oracle.egg-info/PKG-INFO
tap_oracle.egg-info/SOURCES.txt
tap_oracle.egg-info/dependency_links.txt
tap_oracle.egg-info/entry_points.txt
tap_oracle.egg-info/requires.txt
tap_oracle.egg-info/top_level.txt
tap_oracle/sync_strategies/__init__.py
tap_oracle/sync_strategies/common.py
tap_oracle/sync_strategies/full_table.py
tap_oracle/sync_strategies/incremental.py
tap_oracle/sync_strategies/log_miner.py
tests/test_currently_syncing.py
tests/test_discovery.py
tests/test_full_table.py
tests/test_full_table_interruption.py
tests/test_log_miner_after_full_table.py
tests/test_log_miner_dates.py
tests/test_log_miner_decimals.py
tests/test_log_miner_floats.py
tests/test_log_miner_integers.py
tests/test_log_miner_strings.py
tests/test_unsupported_pk.py