Metadata-Version: 2.1
Name: tap-oracle
Version: 1.3.0
Summary: Singer.io tap for extracting data from Oracle
Home-page: https://singer.io
Author: Stitch
Classifier: Programming Language :: Python :: 3 :: Only
License-File: LICENSE
Requires-Dist: singer-python==6.1.0
Requires-Dist: cx_Oracle==6.1
Requires-Dist: strict-rfc3339==0.7
Provides-Extra: dev
Requires-Dist: pylint; extra == "dev"
